pib_sdk/__init__.py
pib_sdk/control.py
pib_sdk/kinematics.py
pib_sdk/pib_DH.py
pib_sdk-1.2.1.dist-info/METADATA
pib_sdk-1.2.1.dist-info/WHEEL
pib_sdk-1.2.1.dist-info/top_level.txt
pib_sdk-1.2.1.dist-info/RECORD
