Metadata-Version: 2.4
Name: pib-sdk
Version: 1.2.1
Summary: Forward & inverse kinematics helpers for pib's robot arms
Author-email: "pib.rocks" <team@pib.rocks>
License:                     GNU AFFERO GENERAL PUBLIC LICENSE
Project-URL: Homepage, https://github.com/pib-rocks/pib-sdk
Classifier: Programming Language :: Python :: 3
Classifier: License :: OSI Approved :: MIT License
Classifier: Operating System :: OS Independent
Requires-Python: >=3.9
Requires-Dist: roboticstoolbox-python==1.1.0
Requires-Dist: numpy<2
Requires-Dist: spatialmath-python
Requires-Dist: roslibpy
Provides-Extra: dev
Requires-Dist: pytest; extra == "dev"
Requires-Dist: ruff; extra == "dev"
Requires-Dist: build; extra == "dev"
Requires-Dist: twine; extra == "dev"
